{"fax": "613-954-2269", "links": [{"url": "http://www.parl.gc.ca/MembersOfParliament/ProfileMP.aspx?Key=188928&Language=E", "note": "Page on parl.gc.ca"}, {"url": "http://alexandrinelatendresse.ndp.ca/about", "note": "Official site"}], "image": "/media/polpics/1823_1.jpg", "other_info": {"favourite_word": ["conservatives"], "wordcloud": ["autoimg/wordcloud-pol/alexandrine-latendresse.png"], "parlinfo_id": ["9bcb731e-774b-4fe3-bb03-8c92f59eaa6c"], "alternate_name": ["alexandrine latendresse"], "constituency_offices": ["6655 Pierre Bertrand Blvd, Suite 220 (Main Office)\nQu\u00e9bec, Qu\u00e9bec\nG2K 1M1\n\nPhone: 418-626-5522\nFax: 418-626-5646\n\n\n"], "parl_id": ["170255", "170980", "188928"]}, "related": {"speeches_url": "/speeches/?politician=alexandrine-latendresse", "ballots_url": "/votes/ballots/?politician=alexandrine-latendresse", "sponsored_bills_url": "/bills/?sponsor_politician=alexandrine-latendresse"}, "family_name": "Latendresse", "name": "Alexandrine Latendresse", "url": "/politicians/alexandrine-latendresse/", "gender": "female", "memberships": [{"end_date": null, "riding": {"province": "QC", "name": {"en": "Louis-Saint-Laurent"}, "id": 24038}, "url": "/politicians/memberships/4058/", "party": {"name": {"en": "New Democratic Party"}, "short_name": {"en": "NDP"}}, "start_date": "2011-05-02", "label": {"en": "NDP MP for Louis-Saint-Laurent"}}], "given_name": "Alexandrine", "voice": "613-996-4151", "email": "Alexandrine.Latendresse@parl.gc.ca"}