{"fax": "613-992-6194", "links": [{"url": "http://www.parl.gc.ca/MembersOfParliament/ProfileMP.aspx?Key=190884&Language=E", "note": "Page on parl.gc.ca"}, {"url": "http://philiptoone.ndp.ca/home", "note": "Official site"}], "image": "/media/polpics/3658_1.jpg", "other_info": {"favourite_word": ["conservatives"], "parlinfo_id": ["288315ef-2fe8-48ad-8ae0-833ac097bac0"], "wordcloud": ["autoimg/wordcloud-pol/philip-toone.png"], "alternate_name": ["philip toone"], "constituency_offices": ["3-1 C\u00f4te Carter (Main Office)\nGasp\u00e9, Qu\u00e9bec\nG4X 1T5\n\nPhone: 418-368-1855\nFax: 418-368-1924\n\n\n735 Principal Road, Suite 208\nCap-aux-Meules, Qu\u00e9bec\nG4T 1G8\n\nPhone: 418-986-5552\nFax: 418-986-5553\n\n\n642-B Perron Blvd.\nCarleton-sur-Mer, Qu\u00e9bec\nG0C 1J0\n\nPhone: 418-364-1401\nFax: 418-364-1406\n\n\n"], "parl_id": ["170311", "173842", "178789", "182460", "170979", "177195", "186495", "185305", "186072", "190884"]}, "related": {"speeches_url": "/speeches/?politician=philip-toone", "ballots_url": "/votes/ballots/?politician=philip-toone", "sponsored_bills_url": "/bills/?sponsor_politician=philip-toone"}, "family_name": "Toone", "name": "Philip Toone", "url": "/politicians/philip-toone/", "gender": "male", "memberships": [{"end_date": null, "riding": {"province": "QC", "name": {"en": "Gasp\u00e9sie\u2014\u00celes-de-la-Madeleine"}, "id": 24019}, "url": "/politicians/memberships/4137/", "party": {"name": {"en": "New Democratic Party"}, "short_name": {"en": "NDP"}}, "start_date": "2011-05-02", "label": {"en": "NDP MP for Gasp\u00e9sie\u2014\u00celes-de-la-Madeleine"}}], "given_name": "Philip", "voice": "613-992-6188", "email": "Philip.Toone@parl.gc.ca"}