{"fax": "613-995-1062", "links": [{"url": "http://www.parl.gc.ca/MembersOfParliament/ProfileMP.aspx?Key=186488&Language=E", "note": "Page on parl.gc.ca"}, {"url": "http://sanahassainia.ndp.ca/about", "note": "Official site"}], "image": "/media/polpics/8692_1.jpg", "other_info": {"twitter": ["SanaNPD"], "twitter_id": ["119932406"], "parlinfo_id": ["ad80aecc-4240-49e0-977b-30b5cf1e31a7"], "alternate_name": ["sana hassainia"], "wordcloud": ["autoimg/wordcloud-pol/sana-hassainia.png"], "constituency_offices": ["2071 Route Marie-Victorin, Suite 118-119 (Main Office)\nVarennes, Qu\u00e9bec\nJ3X 1R3\n\nPhone: 450-652-4442\nFax: 450-652-4447\n\n\n"], "favourite_word": ["workers"], "parl_id": ["170636", "173812", "186488"]}, "related": {"speeches_url": "/speeches/?politician=sana-hassainia", "ballots_url": "/votes/ballots/?politician=sana-hassainia", "sponsored_bills_url": "/bills/?sponsor_politician=sana-hassainia"}, "family_name": "Hassainia", "name": "Sana Hassainia", "url": "/politicians/sana-hassainia/", "gender": "female", "memberships": [{"end_date": null, "riding": {"province": "QC", "name": {"en": "Verch\u00e8res\u2014Les Patriotes"}, "id": 24074}, "url": "/politicians/memberships/4036/", "party": {"name": {"en": "New Democratic Party"}, "short_name": {"en": "NDP"}}, "start_date": "2011-05-02", "label": {"en": "NDP MP for Verch\u00e8res\u2014Les Patriotes"}}], "given_name": "Sana", "voice": "613-996-2998", "email": "Sana.Hassainia@parl.gc.ca"}