{"attribution": {"fr": "", "en": "Mr. Deepak Obhrai (Parliamentary Secretary to the Minister of Foreign Affairs, CPC)"}, "politician_url": "/politicians/deepak-obhrai/", "url": "/debates/2013/6/11/deepak-obhrai-2/", "h1": {"fr": "", "en": "Oral Questions"}, "related": {"document_speeches_url": "/speeches/?document=%2Fdebates%2F2013%2F6%2F11%2F"}, "content": {"fr": "<p data-HoCid=\"3401463\" data-originallang=\"en\">Monsieur le Pr\u00e9sident, je viens de dire que le Canada est heureux de jouer un r\u00f4le de premier plan. Le Canada est un chef de file mondial en mati\u00e8re de protection et de promotion des droits des femmes et des filles. Nous continuons de prendre des mesures concr\u00e8tes afin d'am\u00e9liorer la vie des femmes et des enfants dans le monde entier. Nous poursuivrons nos efforts en ce sens sur la sc\u00e8ne internationale, mais nous devons surtout respecter les lois canadiennes, et c'est ce que nous ferons.</p>", "en": "<p data-HoCid=\"3401463\" data-originallang=\"en\">Mr. Speaker, as I just said, Canada is pleased to take a leadership role. Canada is a world leader in the protection and promotion of rights of women and girls. We continue to focus on concrete measures in the different lives of women and children around the world. We will continue doing this on the international stage. However, most important, we have to comply with our laws in our country and that is what we will do.</p>"}, "h2": {"fr": "", "en": "Foreign Affairs"}, "document_url": "/debates/2013/6/11/", "time": "2013-06-11 14:55:00", "source_id": "8074873", "politician_membership_url": "/politicians/memberships/1236/", "procedural": false}