{"attribution": {"fr": "", "en": "Hon. Peter MacKay (Minister of National Defence, CPC)"}, "politician_url": "/politicians/peter-mackay/", "url": "/debates/2013/6/11/peter-mackay-6/", "h1": {"fr": "", "en": "Oral Questions"}, "related": {"document_speeches_url": "/speeches/?document=%2Fdebates%2F2013%2F6%2F11%2F"}, "content": {"fr": "<p data-HoCid=\"3401423\" data-originallang=\"en\">Oui, monsieur le Pr\u00e9sident, j'ai d\u00e9j\u00e0 r\u00e9pondu \u00e0 cette question. En fait, aucun militaire bless\u00e9 n'est lib\u00e9r\u00e9 des forces arm\u00e9es avant d'\u00eatre pr\u00eat \u00e0 le faire. Les militaires collaborent \u00e0 l'\u00e9laboration de leur plan de transition avec des membres des Forces arm\u00e9es canadiennes jusqu'\u00e0 ce qu'ils soient pr\u00eats \u00e0 \u00eatre lib\u00e9r\u00e9s. Lorsque le moment est venu pour leur famille et qu'ils sont pr\u00eats \u00e0 passer au secteur priv\u00e9, il existe un programme sp\u00e9cialement con\u00e7u pour faciliter cette transition. Tant que je serai l\u00e0, c'est ainsi que les choses se passeront pour le caporal Kirkland et pour les militaires bless\u00e9s des Forces canadiennes.</p>", "en": "<p data-HoCid=\"3401423\" data-originallang=\"en\">Yes, Mr. Speaker, I have already answered that question. In fact, all injured members are not released from the military until they are prepared to do so. Until they are prepared for release, they work with members of the Canadian Forces on their transition plans. When it is appropriate for their families and they are ready to make a shift into the private sector, there is a program specifically designed to help with that transition. That will be the case for Corporal Kirkland. That will be the case for injured members of the Canadian Forces on my watch.</p>"}, "h2": {"fr": "", "en": "National Defence"}, "document_url": "/debates/2013/6/11/", "time": "2013-06-11 14:40:00", "source_id": "8074820", "politician_membership_url": "/politicians/memberships/1332/", "procedural": false}